{
    "Model path": "../../SP7UnityEditor/Assets/Graphics/TintedModels/Pokeball/pokeball.fbx",
    "Tints": [
        {
            "Tint1-Primary-Red Channel": "",
            "Red": 0.0,
            "Green": 0.23529411852359773,
            "Blue": 1.0,
            "Alpha": 0.0,
            "Texture": "../../SP7UnityEditor/Assets/Graphics/Textures/Shared/orchid1.dds"
        },
        {
            "Tint2-Secondary-Green Channel": "",
            "Red": 0.0,
            "Green": 0.23529411852359773,
            "Blue": 1.0,
            "Alpha": 1.0,
            "Texture": ""
        },
        {
            "Tint3-Tertiary-Blue Channel": "",
            "Red": 0.25929930806159975,
            "Green": 0.29173848032951357,
            "Blue": 0.5343137383460999,
            "Alpha": 1.0,
            "Texture": "../../SP7UnityEditor/Assets/Graphics/Textures/Shared/blue.dds"
        },
        {
            "Tint4-Accents-Alpha Channel": "",
            "Red": 1.0,
            "Green": 0.7490196228027344,
            "Blue": 0.0,
            "Alpha": 0.0,
            "Texture": "../../SP7UnityEditor/Assets/Graphics/Textures/Shared/orchid2.dds"
        }
    ],
    "Emissive": {
        "Red": 0.9047861099243164,
        "Green": 0.46078431606292727,
        "Blue": 1.0,
        "Alpha": 1.0
    }
}