{"links":[{"colorsPath":"Assets\\Generated\\PolybrushColors_-47890_Bin.bin","myTransformIDs":[-47898],"myMaterialNames":["EN_G_Floor1_lv1_1_clean","EN_G_Floor1_lv1_1_brokenWood","EN_G_Floor1_lv1_1_wood"]},{"colorsPath":"Assets\\Generated\\PolybrushColors_-48030_Bin.bin","myTransformIDs":[-48052],"myMaterialNames":["EN_G_Floor1_lv1_1_clean","EN_G_Floor1_lv1_1_brokenWood","EN_G_Floor1_lv1_1_wood"]},{"colorsPath":"Assets\\Generated\\PolybrushColors_-48034_Bin.bin","myTransformIDs":[-48042],"myMaterialNames":["EN_G_Floor1_lv1_1_clean","EN_G_Floor1_lv1_1_brokenWood","EN_G_Floor1_lv1_1_wood"]},{"colorsPath":"Assets\\Generated\\PolybrushColors_-47784_Bin.bin","myTransformIDs":[-47792],"myMaterialNames":["EN_G_Floor1_lv1_1_clean","EN_G_Floor1_lv1_1_brokenWood","EN_G_Floor1_lv1_1_wood"]},{"colorsPath":"Assets\\Generated\\PolybrushColors_-25710_Bin.bin","myTransformIDs":[-46108],"myMaterialNames":["EN_W_Wall_lv1_1_Dirty","EN_W_Wall_lv1_1_Worn","EN_W_Wall_lv1_1_Clean"]},{"colorsPath":"Assets\\Generated\\PolybrushColors_-25816_Bin.bin","myTransformIDs":[-46206],"myMaterialNames":["EN_W_Wall_lv1_1_Dirty","EN_W_Wall_lv1_1_Worn","EN_W_Wall_lv1_1_Clean"]},{"colorsPath":"Assets\\Generated\\PolybrushColors_-26046_Bin.bin","myTransformIDs":[-46324],"myMaterialNames":["EN_W_Wall_lv1_1_Dirty","EN_W_Wall_lv1_1_Worn","EN_W_Wall_lv1_1_Clean"]},{"colorsPath":"Assets\\Generated\\PolybrushColors_-26050_Bin.bin","myTransformIDs":[-46522],"myMaterialNames":["EN_W_Wall_lv1_1_Dirty","EN_W_Wall_lv1_1_Worn","EN_W_Wall_lv1_1_Clean"]}]}